tensorly_sphinx_theme/__init__.py
tensorly_sphinx_theme/analytics.html
tensorly_sphinx_theme/footer.html
tensorly_sphinx_theme/layout.html
tensorly_sphinx_theme/localtoc.html
tensorly_sphinx_theme/navigation.html
tensorly_sphinx_theme/pagination.html
tensorly_sphinx_theme/search.html
tensorly_sphinx_theme/searchbox.html
tensorly_sphinx_theme/sidebar-menu.html
tensorly_sphinx_theme/theme.conf
tensorly_sphinx_theme/static/navbar_burger.js
tensorly_sphinx_theme/static/tensorly_style.css
tensorly_sphinx_theme-0.2.3.dist-info/METADATA
tensorly_sphinx_theme-0.2.3.dist-info/WHEEL
tensorly_sphinx_theme-0.2.3.dist-info/entry_points.txt
tensorly_sphinx_theme-0.2.3.dist-info/top_level.txt
tensorly_sphinx_theme-0.2.3.dist-info/RECORD
