Metadata-Version: 2.1
Name: tensorly-sphinx-theme
Version: 0.2.3
Summary: Bulma-based Sphinx theme from the TensorLy project.
Home-page: https://github.com/tensorly/tensorly-sphinx-theme
Author: Jean Kossaifi
Author-email: jean.kossaifi@gmail.com
License: Modified BSD
Classifier: Topic :: Scientific/Engineering
Classifier: Programming Language :: Python :: 3
Classifier: Development Status :: 4 - Beta
Classifier: Framework :: Sphinx
Classifier: Framework :: Sphinx :: Theme
Requires-Dist: sphinx
